senpy/__init__.py
senpy/confidence.py
senpy/log_logistic_funcs.py
senpy/logistic_funcs.py
senpy/neyer.py
senpy/norm_funcs.py
senpy/plotting.py
senpy/utils.py
senpy_sensei-1.3.1.dist-info/LICENSE
senpy_sensei-1.3.1.dist-info/METADATA
senpy_sensei-1.3.1.dist-info/WHEEL
senpy_sensei-1.3.1.dist-info/top_level.txt
senpy_sensei-1.3.1.dist-info/RECORD
