Metadata-Version: 2.1
Name: senpy-sensei
Version: 1.3.1
Summary: A python package of algorithms for sensitivity testing.
Project-URL: Repository, https://github.com/ACasey13/senpy
Classifier: Programming Language :: Python :: 3
Classifier: License :: OSI Approved :: MIT License
Classifier: Operating System :: OS Independent
License-File: LICENSE
Requires-Dist: scipy
Requires-Dist: numpy
Requires-Dist: scikit-image
Requires-Dist: matplotlib
